Sanga/__init__.py
Sanga/config.py
Sanga/factory.py
Sanga/struct.py
Sanga/media/__init__.py
Sanga/media/appledaily.py
Sanga/media/base.py
Sanga/media/bcc.py
Sanga/media/bnext.py
Sanga/media/chinatimes.py
Sanga/media/cmmedia.py
Sanga/media/cna.py
Sanga/media/cnews.py
Sanga/media/cnyes.py
Sanga/media/ctee.py
Sanga/media/ctitv.py
Sanga/media/cts.py
Sanga/media/ctv.py
Sanga/media/digitimes.py
Sanga/media/ebc.py
Sanga/media/epochtimes.py
Sanga/media/eracom.py
Sanga/media/ettoday.py
Sanga/media/ftvnews.py
Sanga/media/kairos.py
Sanga/media/ltn.py
Sanga/media/mirrormedia.py
Sanga/media/moneydj.py
Sanga/media/moneyudn.py
Sanga/media/mypeoplevol.py
Sanga/media/newtalk.py
Sanga/media/nownews.py
Sanga/media/pchome.py
Sanga/media/peoplenews.py
Sanga/media/pts.py
Sanga/media/rti.py
Sanga/media/setn.py
Sanga/media/sina.py
Sanga/media/storm.py
Sanga/media/taiwanhot.py
Sanga/media/taronews.py
Sanga/media/technews.py
Sanga/media/thenewslens.py
Sanga/media/ttv.py
Sanga/media/tvbs.py
Sanga/media/udn.py
Sanga/media/upmedia.py
Sanga/media/ustv.py
Sanga/media/wantrich.py
Sanga/media/wealth.py
Sanga/media/worldjournal.py
Sanga/media/yahoo.py
Sanga-0.0.1.dev4.dist-info/LICENSE
Sanga-0.0.1.dev4.dist-info/METADATA
Sanga-0.0.1.dev4.dist-info/WHEEL
Sanga-0.0.1.dev4.dist-info/top_level.txt
Sanga-0.0.1.dev4.dist-info/RECORD
